pscodeanalyzer/__init__.py
pscodeanalyzer/engine.py
pscodeanalyzer/rules/__init__.py
pscodeanalyzer/rules/peoplecode.py
pscodeanalyzer-1.2.3.dist-info/LICENSE.txt
pscodeanalyzer-1.2.3.dist-info/METADATA
pscodeanalyzer-1.2.3.dist-info/WHEEL
pscodeanalyzer-1.2.3.dist-info/top_level.txt
pscodeanalyzer-1.2.3.dist-info/RECORD
