Metadata-Version: 2.1
Name: pscodeanalyzer
Version: 1.2.3
Summary: A static code analyzer with configurable plug-in rules
Home-page: https://github.com/lbaca/PSCodeAnalyzer
Author: Leandro Baca
Author-email: leandrobaca77@gmail.com
License: UNKNOWN
Keywords: peoplesoft peoplecode source application-class application-package code-analysis code-review
Platform: UNKNOWN
Classifier: Development Status :: 5 - Production/Stable
Classifier: Environment :: Console
Classifier: Intended Audience :: Developers
Classifier: Intended Audience :: Information Technology
Classifier: Programming Language :: Python :: 3
Classifier: Programming Language :: Python :: 3.6
Classifier: Programming Language :: Python :: 3.7
Classifier: Programming Language :: Python :: 3.8
Classifier: Programming Language :: Python :: 3.9
Classifier: License :: OSI Approved :: MIT License
Classifier: Operating System :: OS Independent
Classifier: Topic :: Software Development
Requires-Python: ~=3.6
Requires-Dist: peoplecodeparser
